u8488a/__init__.py
u8488a/base.py
u8488a/usrp.py
u8488a-0.1.2.dist-info/METADATA
u8488a-0.1.2.dist-info/WHEEL
u8488a-0.1.2.dist-info/top_level.txt
u8488a-0.1.2.dist-info/RECORD
