Metadata-Version: 2.1
Name: u8488a
Version: 0.1.2
Summary: Keysight U8488A Powermeter Driver for USRP Power Calibration
Home-page: https://github.com/anilgurses/U8488A_USRP_Calibration.git
Author: Anıl Gürses
Author-email: agurses@ncsu.edu
License: MIT
